WeiruanGuanfangNetZhinan20171224/README.md
WeiruanGuanfangNetZhinan20171224/__init__.py
WeiruanGuanfangNetZhinan20171224/__main__.py
WeiruanGuanfangNetZhinan20171224/file.epub
WeiruanGuanfangNetZhinan20171224/index.html
WeiruanGuanfangNetZhinan20171224/css/__init__.py
WeiruanGuanfangNetZhinan20171224/css/annotations.css
WeiruanGuanfangNetZhinan20171224/css/main.css
WeiruanGuanfangNetZhinan20171224/css/normalize.css
WeiruanGuanfangNetZhinan20171224/css/popup.css
WeiruanGuanfangNetZhinan20171224/font/__init__.py
WeiruanGuanfangNetZhinan20171224/font/fontello.eot
WeiruanGuanfangNetZhinan20171224/font/fontello.svg
WeiruanGuanfangNetZhinan20171224/font/fontello.ttf
WeiruanGuanfangNetZhinan20171224/font/fontello.woff
WeiruanGuanfangNetZhinan20171224/img/__init__.py
WeiruanGuanfangNetZhinan20171224/img/annotator-glyph-sprite.png
WeiruanGuanfangNetZhinan20171224/img/annotator-icon-sprite.png
WeiruanGuanfangNetZhinan20171224/img/apple-touch-icon.png
WeiruanGuanfangNetZhinan20171224/img/cancelfullscreen.png
WeiruanGuanfangNetZhinan20171224/img/close.png
WeiruanGuanfangNetZhinan20171224/img/fullscreen.png
WeiruanGuanfangNetZhinan20171224/img/loader.gif
WeiruanGuanfangNetZhinan20171224/img/menu-icon.png
WeiruanGuanfangNetZhinan20171224/img/save.png
WeiruanGuanfangNetZhinan20171224/img/saved.png
WeiruanGuanfangNetZhinan20171224/img/settings-s.png
WeiruanGuanfangNetZhinan20171224/img/settings.png
WeiruanGuanfangNetZhinan20171224/img/star.png
WeiruanGuanfangNetZhinan20171224/js/__init__.py
WeiruanGuanfangNetZhinan20171224/js/epub.js
WeiruanGuanfangNetZhinan20171224/js/epub.min.js
WeiruanGuanfangNetZhinan20171224/js/epub.min.map
WeiruanGuanfangNetZhinan20171224/js/hooks.min.js
WeiruanGuanfangNetZhinan20171224/js/hooks.min.map
WeiruanGuanfangNetZhinan20171224/js/reader.js
WeiruanGuanfangNetZhinan20171224/js/reader.js.map
WeiruanGuanfangNetZhinan20171224/js/reader.min.js
WeiruanGuanfangNetZhinan20171224/js/reader.min.map
WeiruanGuanfangNetZhinan20171224/js/hooks/__init__.py
weiruan_guanfang_net_zhinan_20171224-2024.3.2.0.dist-info/METADATA
weiruan_guanfang_net_zhinan_20171224-2024.3.2.0.dist-info/WHEEL
weiruan_guanfang_net_zhinan_20171224-2024.3.2.0.dist-info/entry_points.txt
weiruan_guanfang_net_zhinan_20171224-2024.3.2.0.dist-info/top_level.txt
weiruan_guanfang_net_zhinan_20171224-2024.3.2.0.dist-info/RECORD
